docker_image_cleaner/__init__.py
docker_image_cleaner/__main__.py
docker_image_cleaner/cleaner.py
docker_image_cleaner-1.0.0b3.dist-info/LICENSE
docker_image_cleaner-1.0.0b3.dist-info/METADATA
docker_image_cleaner-1.0.0b3.dist-info/WHEEL
docker_image_cleaner-1.0.0b3.dist-info/entry_points.txt
docker_image_cleaner-1.0.0b3.dist-info/top_level.txt
docker_image_cleaner-1.0.0b3.dist-info/RECORD
