Metadata-Version: 2.1
Name: docker-image-cleaner
Version: 1.0.0b3
Summary: Cleanup old docker images to free up disk space and inodes
Home-page: https://github.com/jupyterhub/docker-image-cleaner
Author: Project Jupyter Contributors
Author-email: jupyter@googlegroups.com
License: BSD
Requires-Python: >=3.8
License-File: LICENSE
Requires-Dist: docker
Requires-Dist: kubernetes
